README.md
setup.cfg
setup.py
olympus/__init__.py
olympus/api.py
olympus/models.py
olympus/olympus.py
olympus/utils.py
olympus.egg-info/PKG-INFO
olympus.egg-info/SOURCES.txt
olympus.egg-info/dependency_links.txt
olympus.egg-info/entry_points.txt
olympus.egg-info/requires.txt
olympus.egg-info/top_level.txt
olympus/adapters/__init__.py
olympus/adapters/keras_adapter.py
olympus/adapters/utils.py
olympus/database/__init__.py
olympus/database/db.py
olympus/storage/__init__.py
olympus/storage/storage.py